CHANGES.rst
CONTRIBUTORS.rst
MANIFEST.in
README.rst
setup.py
cpskin/__init__.py
cpskin.minisite.egg-info/PKG-INFO
cpskin.minisite.egg-info/SOURCES.txt
cpskin.minisite.egg-info/dependency_links.txt
cpskin.minisite.egg-info/not-zip-safe
cpskin.minisite.egg-info/requires.txt
cpskin.minisite.egg-info/top_level.txt
cpskin/minisite/__init__.py
cpskin/minisite/configure.zcml
cpskin/minisite/controlpanel.py
cpskin/minisite/event.py
cpskin/minisite/interfaces.py
cpskin/minisite/minisite.py
cpskin/minisite/minisite_dropdown_menu.pt
cpskin/minisite/minisite_dropdown_menu_recurse.pt
cpskin/minisite/minisite_in_minisite.pt
cpskin/minisite/minisite_menu.pt
cpskin/minisite/minisites_panel.pt
cpskin/minisite/portlet.pt
cpskin/minisite/portlet.py
cpskin/minisite/search_in_minisite.pt
cpskin/minisite/searchbox_in_minisite.pt
cpskin/minisite/setuphandlers.py
cpskin/minisite/startup.py
cpskin/minisite/testing.py
cpskin/minisite/testing.zcml
cpskin/minisite/transform.py
cpskin/minisite/traverser.py
cpskin/minisite/upgradehandlers.py
cpskin/minisite/utils.py
cpskin/minisite/viewlet.py
cpskin/minisite/browser/__init__.py
cpskin/minisite/browser/configure.zcml
cpskin/minisite/browser/hnavigation.py
cpskin/minisite/browser/interfaces.py
cpskin/minisite/browser/navigation.py
cpskin/minisite/profiles/default/actions.xml
cpskin/minisite/profiles/default/browserlayer.xml
cpskin/minisite/profiles/default/controlpanel.xml
cpskin/minisite/profiles/default/metadata.xml
cpskin/minisite/profiles/default/portlets.xml
cpskin/minisite/profiles/default/viewlets.xml
cpskin/minisite/profiles/testing/metadata.xml
cpskin/minisite/profiles/testing/register_cpskin_minisites.txt
cpskin/minisite/profiles/uninstall/browserlayer.xml
cpskin/minisite/profiles/uninstall/controlpanel.xml
cpskin/minisite/profiles/uninstall/portlets.xml
cpskin/minisite/profiles/uninstall/viewlets.xml
cpskin/minisite/tests/__init__.py
cpskin/minisite/tests/minisites_config.txt
cpskin/minisite/tests/robot_test.txt
cpskin/minisite/tests/test_example.py
cpskin/minisite/tests/test_profiles.py
cpskin/minisite/tests/test_robot.py
cpskin/minisite/tests/test_viewlet.py
cpskin/minisite/upgrades/to0003/actions.xml
docs/LICENSE.GPL
docs/LICENSE.rst