Metadata-Version: 2.1
Name: cpskin.minisite
Version: 1.1.7
Summary: UI for sections configured with their own domain
Home-page: https://github.com/imio/
Author: IMIO
Author-email: support@imio.be
License: gpl
Platform: UNKNOWN
Classifier: Environment :: Web Environment
Classifier: Operating System :: OS Independent
Classifier: Framework :: Zope2
Classifier: Framework :: Plone
Classifier: Framework :: Plone :: 4.2
Classifier: Framework :: Plone :: 4.3
Classifier: Programming Language :: Python
Classifier: Programming Language :: Python :: 2.6
Classifier: Programming Language :: Python :: 2.7
Classifier: Topic :: Software Development :: Libraries :: Python Modules
Provides-Extra: test
